key_interactions_finder/__init__.py
key_interactions_finder/chimerax_projections.py
key_interactions_finder/contact_identification.py
key_interactions_finder/data_preperation.py
key_interactions_finder/model_building.py
key_interactions_finder/network_analysis.py
key_interactions_finder/post_proccessing.py
key_interactions_finder/project_structure_utils.py
key_interactions_finder/pycontact_processing.py
key_interactions_finder/pymol_projections.py
key_interactions_finder/stat_modelling.py
key_interactions_finder/utils.py
key_interactions_finder/model_params/gridsearch_custom.json
key_interactions_finder/model_params/gridsearch_exhaustive.json
key_interactions_finder/model_params/gridsearch_moderate.json
key_interactions_finder/model_params/gridsearch_none.json
key_interactions_finder/model_params/gridsearch_quick.json
kif-0.4.2.dist-info/licenses/LICENSE.md
kif-0.4.2.dist-info/METADATA
kif-0.4.2.dist-info/WHEEL
kif-0.4.2.dist-info/top_level.txt
kif-0.4.2.dist-info/RECORD
