Metadata-Version: 2.4
Name: KIF
Version: 0.4.2
Summary: Python package for MD simulation analysis
Author-email: Rory Crean <rory.crean@icm.uu.se>
Project-URL: homepage, https://github.com/kamerlinlab/KIF
Project-URL: docs, https://kamerlinlab.github.io/KIF/
Requires-Python: >=3.10
License-File: LICENSE.md
Requires-Dist: catboost>=1.2.8
Requires-Dist: gdown>=5.2.0
Requires-Dist: ipykernel>=6.29.5
Requires-Dist: jupyter>=1.1.1
Requires-Dist: mdanalysis>=2.9.0
Requires-Dist: mdanalysistests>=2.9.0
Requires-Dist: numpy>=2.2.5
Requires-Dist: pandas>=2.2.3
Requires-Dist: scikit-learn>=1.6.1
Requires-Dist: scipy>=1.15.2
Requires-Dist: xgboost>=3.0.0
Dynamic: license-file
